orphism/__init__.py
orphism/__main__.hy
orphism/bucket.hy
orphism/line.hy
orphism-0.0.1.dev4.dist-info/LICENSE.txt
orphism-0.0.1.dev4.dist-info/METADATA
orphism-0.0.1.dev4.dist-info/WHEEL
orphism-0.0.1.dev4.dist-info/entry_points.txt
orphism-0.0.1.dev4.dist-info/top_level.txt
orphism-0.0.1.dev4.dist-info/RECORD
