Metadata-Version: 2.1
Name: orphism
Version: 0.0.1.dev4
Home-page: https://github.com/kunalb/orphism
Classifier: Programming Language :: Python :: 3
Classifier: License :: OSI Approved :: MIT License
Classifier: Operating System :: OS Independent
Classifier: Development Status :: 3 - Alpha
Requires-Python: >=3.8
License-File: LICENSE.txt
Requires-Dist: hy >=0.27.0
Requires-Dist: hyrule >=0.4.0
Requires-Dist: rich >=12.6.0
